GeoUsage/__init__.py
GeoUsage/log.py
GeoUsage/mailing_list.py
GeoUsage-0.1.0.dist-info/LICENSE
GeoUsage-0.1.0.dist-info/METADATA
GeoUsage-0.1.0.dist-info/WHEEL
GeoUsage-0.1.0.dist-info/entry_points.txt
GeoUsage-0.1.0.dist-info/top_level.txt
GeoUsage-0.1.0.dist-info/RECORD
