Metadata-Version: 2.1
Name: GeoUsage
Version: 0.1.0
Summary: GeoUsage is a pure Python package to read and write NASA Southern Hemisphere ADditional OZonesondes (SHADOZ) data.
Home-page: https://github.com/geopython/GeoUsage
Author: Meteorological Service of Canada
Author-email: tom.kralidis@canada.ca
Maintainer: Meteorological Service of Canada
Maintainer-email: tom.kralidis@canada.ca
License: MIT
Keywords: geospatial metrics log analysis ows
Platform: all
Classifier: Development Status :: 4 - Beta
Classifier: Environment :: Console
Classifier: Intended Audience :: Developers
Classifier: Intended Audience :: Science/Research
Classifier: License :: OSI Approved :: MIT License
Classifier: Operating System :: OS Independent
Classifier: Programming Language :: Python
Requires-Dist: click
Requires-Dist: requests
